easyflowutils/__init__.py
easyflowutils/decorators.py
easyflowutils/fireberry_client.py
easyflowutils/func_deployer.py
easyflowutils/general_helpers.py
easyflowutils/logger_utils.py
easyflowutils/manychat_client.py
easyflowutils/schooler_client.py
tests/__init__.py
tests/test_fireberry_client.py
tests/test_schooler_client.py
upgrade/__init__.py
upgrade/update_package.py
easyflowutils-0.2.81.dist-info/LICENSE
easyflowutils-0.2.81.dist-info/METADATA
easyflowutils-0.2.81.dist-info/WHEEL
easyflowutils-0.2.81.dist-info/top_level.txt
easyflowutils-0.2.81.dist-info/RECORD
